<?xml version="1.0" encoding="UTF-8" standalone="yes"?>
<classroomes>
    <classroom>
        <id>1</id>
        <ma>A02</ma>
        <ten>Phòng A02</ten>
        <loaiPhong>Phòng máy</loaiPhong>
        <sucChua>32</sucChua>
        <diaChi>B2</diaChi>
        <csvc>
            <csvcName>Điều hòa</csvcName>
            <csvcName>Máy tính</csvcName>
        </csvc>
    </classroom>
    <classroom>
        <id>2</id>
        <ma>A03</ma>
        <ten>Phòng A03</ten>
        <loaiPhong>Phòng máy</loaiPhong>
        <sucChua>500</sucChua>
        <diaChi>B1</diaChi>
        <csvc>
            <csvcName>Điều hòa</csvcName>
            <csvcName>Máy tính</csvcName>
        </csvc>
    </classroom>
    <classroom>
        <id>3</id>
        <ma>asd</ma>
        <ten>das</ten>
        <loaiPhong>Phòng máy</loaiPhong>
        <sucChua>21</sucChua>
        <diaChi>das</diaChi>
        <csvc>
            <csvcName>Điều hòa</csvcName>
        </csvc>
    </classroom>
    <classroom>
        <id>4</id>
        <ma>dsa</ma>
        <ten>asd</ten>
        <loaiPhong>Phòng máy</loaiPhong>
        <sucChua>32</sucChua>
        <diaChi>dasdas</diaChi>
        <csvc>
            <csvcName>Điều hòa</csvcName>
        </csvc>
    </classroom>
</classroomes>
